[
{"name": "fchinf","type": "DATE","mode": "NULLABLE"},
{"name": "nrocns","type": "INTEGER","mode": "NULLABLE"},
{"name": "fchini","type": "DATE","mode": "NULLABLE"},
{"name": "fchvto","type": "DATE","mode": "NULLABLE"},
{"name": "fchliq","type": "DATE","mode": "NULLABLE"},
{"name": "tipoop","type": "STRING","mode": "NULLABLE"},
{"name": "contraparte","type": "STRING","mode": "NULLABLE"},
{"name": "numcontratos","type": "NUMERIC","mode": "NULLABLE"},
{"name": "tipoliq","type": "STRING","mode": "NULLABLE"},
{"name": "numopera","type": "STRING","mode": "NULLABLE"},
{"name": "objope","type": "STRING","mode": "NULLABLE"},
{"name": "pais","type": "STRING","mode": "NULLABLE"},
{"name": "monprima","type": "NUMERIC","mode": "NULLABLE"},
{"name": "monsecun","type": "NUMERIC","mode": "NULLABLE"},
{"name": "precontrato","type": "NUMERIC","mode": "NULLABLE"},
{"name": "preconteod","type": "NUMERIC","mode": "NULLABLE"},
{"name": "preciotit","type": "NUMERIC","mode": "NULLABLE"},
{"name": "montocont","type": "NUMERIC","mode": "NULLABLE"},
{"name": "plazo","type": "NUMERIC","mode": "NULLABLE"},
{"name": "dxv","type": "INTEGER","mode": "NULLABLE"},
{"name": "tasvpzo","type": "NUMERIC","mode": "NULLABLE"},
{"name": "pzomisdia","type": "INTEGER","mode": "NULLABLE"},
{"name": "fchtas","type": "DATE","mode": "NULLABLE"},
{"name": "cvestapar","type": "NUMERIC","mode": "NULLABLE"},
{"name": "indfchini","type": "NUMERIC","mode": "NULLABLE"},
{"name": "nomint","type": "STRING","mode": "NULLABLE"},
{"name": "codsta","type": "STRING","mode": "NULLABLE"},
{"name": "fecreg","type": "DATE","mode": "NULLABLE"},
{"name": "horreg","type": "STRING","mode": "NULLABLE"},
{"name": "codusu","type": "STRING","mode": "NULLABLE"},
{"name": "cveprod","type": "STRING","mode": "NULLABLE"},
{"name": "num_paist","type": "INTEGER","mode": "NULLABLE"},
{"name": "monedat","type": "STRING","mode": "NULLABLE"},
{"name": "segccl","type": "STRING","mode": "NULLABLE"},
{"name": "ctacbal","type": "NUMERIC","mode": "NULLABLE"},
{"name": "codauxb","type": "NUMERIC","mode": "NULLABLE"},
{"name": "numauxb","type": "STRING","mode": "NULLABLE"},
{"name": "cgrcaba","type": "STRING","mode": "NULLABLE"},
{"name": "ctacmtm","type": "NUMERIC","mode": "NULLABLE"},
{"name": "codauxm","type": "NUMERIC","mode": "NULLABLE"},
{"name": "numauxm","type": "STRING","mode": "NULLABLE"},
{"name": "cgrcamt","type": "STRING","mode": "NULLABLE"},
{"name": "grupohsbc","type": "STRING","mode": "NULLABLE"},
{"name": "nroins","type": "NUMERIC","mode": "NULLABLE"},
{"name": "nroemp","type": "NUMERIC","mode": "NULLABLE"},
{"name": "dlmemo","type": "NUMERIC","mode": "NULLABLE"},
{"name": "mtm","type": "NUMERIC","mode": "NULLABLE"},
{"name": "nprofit","type": "INTEGER","mode": "NULLABLE"},
{"name": "gho_cust","type": "STRING","mode": "NULLABLE"},
{"name": "dmemo","type": "STRING","mode": "NULLABLE"},
{"name": "contr_code","type": "STRING","mode": "NULLABLE"},
{"name": "exch_code","type": "STRING","mode": "NULLABLE"},
{"name": "fech_ven","type": "STRING","mode": "NULLABLE"},
{"name": "contr_des","type": "STRING","mode": "NULLABLE"},
{"name": "clear_id","type": "STRING","mode": "NULLABLE"},
{"name": "name_cle_id","type": "STRING","mode": "NULLABLE"},
{"name": "broke_id","type": "STRING","mode": "NULLABLE"},
{"name": "broker_name","type": "STRING","mode": "NULLABLE"},
{"name": "contract_cod","type": "STRING","mode": "NULLABLE"},
{"name": "contract_amo","type": "NUMERIC","mode": "NULLABLE"},
{"name": "categoria","type": "STRING","mode": "NULLABLE"},
{"name": "sec_master","type": "STRING","mode": "NULLABLE"},
{"name": "fec_crea_mod","type": "DATE","mode": "NULLABLE"},
{"name": "a1nlot","type": "NUMERIC","mode": "NULLABLE"}

]