[
{"name": "fchinf","type": "DATE","mode": "NULLABLE"},
{"name": "tipo_etiq","type": "INTEGER","mode": "NULLABLE"},
{"name": "submodalidad","type": "INTEGER","mode": "NULLABLE"},
{"name": "no_cred","type": "NUMERIC","mode": "NULLABLE"},
{"name": "nromon","type": "INTEGER","mode": "NULLABLE"},
{"name": "fec_alta","type": "DATE","mode": "NULLABLE"},
{"name": "fec_vto","type": "DATE","mode": "NULLABLE"},
{"name": "imp_cred","type": "NUMERIC","mode": "NULLABLE"},
{"name": "percap","type": "INTEGER","mode": "NULLABLE"},
{"name": "tasa_cobr","type": "NUMERIC","mode": "NULLABLE"},
{"name": "num_amort","type": "INTEGER","mode": "NULLABLE"},
{"name": "plazo","type": "INTEGER","mode": "NULLABLE"},
{"name": "diasmeses","type": "NUMERIC","mode": "NULLABLE"},
{"name": "tasa_fondeo","type": "NUMERIC","mode": "NULLABLE"},
{"name": "tasa_break","type": "NUMERIC","mode": "NULLABLE"},
{"name": "sdo_capital","type": "NUMERIC","mode": "NULLABLE"},
{"name": "fec_ult_usgaap","type": "INTEGER","mode": "NULLABLE"},
{"name": "cve_st","type": "STRING","mode": "NULLABLE"},
{"name": "st_usgaap","type": "INTEGER","mode": "NULLABLE"},
{"name": "fec_recuper","type": "DATE","mode": "NULLABLE"},
{"name": "tasa_recuper","type": "NUMERIC","mode": "NULLABLE"},
{"name": "factor_desc","type": "NUMERIC","mode": "NULLABLE"},
{"name": "tasa_break_gb","type": "NUMERIC","mode": "NULLABLE"},
{"name": "factor_desc_gb","type": "NUMERIC","mode": "NULLABLE"}

]