[
{"name": "fchinf","type": "DATE","mode": "NULLABLE"},
{"name": "nrocns","type": "INTEGER","mode": "NULLABLE"},
{"name": "group_mem_abbr","type": "STRING","mode": "NULLABLE"},
{"name": "branch_num","type": "INTEGER","mode": "NULLABLE"},
{"name": "batch_DATE","type": "DATE","mode": "NULLABLE"},
{"name": "prof_centr_mne","type": "STRING","mode": "NULLABLE"},
{"name": "deal_pos_num","type": "INTEGER","mode": "NULLABLE"},
{"name": "sub_prof_centr","type": "INTEGER","mode": "NULLABLE"},
{"name": "sec_master_num","type": "STRING","mode": "NULLABLE"},
{"name": "sec_line_num","type": "STRING","mode": "NULLABLE"},
{"name": "dealing_num","type": "STRING","mode": "NULLABLE"},
{"name": "accou_prod_typ","type": "STRING","mode": "NULLABLE"},
{"name": "indev_type_val","type": "STRING","mode": "NULLABLE"},
{"name": "sec_descrip","type": "STRING","mode": "NULLABLE"},
{"name": "compra_venta","type": "STRING","mode": "NULLABLE"},
{"name": "origen","type": "STRING","mode": "NULLABLE"},
{"name": "prod_currency","type": "STRING","mode": "NULLABLE"},
{"name": "deal_DATE","type": "DATE","mode": "NULLABLE"},
{"name": "value_DATE","type": "DATE","mode": "NULLABLE"},
{"name": "rep_rrep_DATE","type": "DATE","mode": "NULLABLE"},
{"name": "days","type": "INTEGER","mode": "NULLABLE"},
{"name": "cntrprty_acron","type": "STRING","mode": "NULLABLE"},
{"name": "securities","type": "NUMERIC","mode": "NULLABLE"},
{"name": "clean_price","type": "NUMERIC","mode": "NULLABLE"},
{"name": "rep_rrep_consi","type": "NUMERIC","mode": "NULLABLE"},
{"name": "interest_rate","type": "NUMERIC","mode": "NULLABLE"},
{"name": "interes","type": "NUMERIC","mode": "NULLABLE"},
{"name": "nominal_value","type": "NUMERIC","mode": "NULLABLE"},
{"name": "dirty_price","type": "NUMERIC","mode": "NULLABLE"},
{"name": "curr_coupon_rt","type": "NUMERIC","mode": "NULLABLE"},
{"name": "last_paid_DATE","type": "DATE","mode": "NULLABLE"},
{"name": "next_paid_DATE","type": "DATE","mode": "NULLABLE"},
{"name": "coupon_accrued","type": "NUMERIC","mode": "NULLABLE"},
{"name": "prem_disc_accr","type": "NUMERIC","mode": "NULLABLE"},
{"name": "mtm","type": "NUMERIC","mode": "NULLABLE"},
{"name": "market_value","type": "NUMERIC","mode": "NULLABLE"},
{"name": "nominal_amort","type": "NUMERIC","mode": "NULLABLE"},
{"name": "gho_cust_class","type": "STRING","mode": "NULLABLE"},
{"name": "factor_amort","type": "NUMERIC","mode": "NULLABLE"},
{"name": "fchreg","type": "DATE","mode": "NULLABLE"},
{"name": "horreg","type": "STRING","mode": "NULLABLE"},
{"name": "usureg","type": "STRING","mode": "NULLABLE"},
{"name": "prod_cur_origen","type": "STRING","mode": "NULLABLE"},
{"name": "nominal","type": "NUMERIC","mode": "NULLABLE"},
{"name": "accrual","type": "NUMERIC","mode": "NULLABLE"},
{"name": "p_d","type": "NUMERIC","mode": "NULLABLE"},
{"name": "mtm_calc","type": "NUMERIC","mode": "NULLABLE"},
{"name": "mkt_value","type": "NUMERIC","mode": "NULLABLE"},
{"name": "monto","type": "NUMERIC","mode": "NULLABLE"},
{"name": "val_nom_mtm","type": "NUMERIC","mode": "NULLABLE"},
{"name": "plazo","type": "INTEGER","mode": "NULLABLE"},
{"name": "cpto_tit_aclme","type": "INTEGER","mode": "NULLABLE"},
{"name": "cpto_mto_aclme","type": "INTEGER","mode": "NULLABLE"},
{"name": "pzo_aclme","type": "INTEGER","mode": "NULLABLE"},
{"name": "posi_id","type": "INTEGER","mode": "NULLABLE"},
{"name": "posi_ten_aclme","type": "NUMERIC","mode": "NULLABLE"},
{"name": "titreci_id","type": "INTEGER","mode": "NULLABLE"},
{"name": "titreci_ten_aclme","type": "NUMERIC","mode": "NULLABLE"},
{"name": "mto_entr_id","type": "INTEGER","mode": "NULLABLE"},
{"name": "mto_entr_ten_aclme","type": "NUMERIC","mode": "NULLABLE"},
{"name": "tot_compras_ten_aclme","type": "NUMERIC","mode": "NULLABLE"},
{"name": "titentr_id","type": "INTEGER","mode": "NULLABLE"},
{"name": "titentr_ten_aclme","type": "NUMERIC","mode": "NULLABLE"},
{"name": "mto_recib_id","type": "INTEGER","mode": "NULLABLE"},
{"name": "mto_recib_ten_aclme","type": "NUMERIC","mode": "NULLABLE"},
{"name": "tot_ventas_ten_aclme","type": "NUMERIC","mode": "NULLABLE"},
{"name": "td_3156_t","type": "NUMERIC","mode": "NULLABLE"},
{"name": "td_3156_825","type": "NUMERIC","mode": "NULLABLE"},
{"name": "td_3156_830","type": "NUMERIC","mode": "NULLABLE"},
{"name": "td_3156_835","type": "NUMERIC","mode": "NULLABLE"},
{"name": "td_3156_815","type": "NUMERIC","mode": "NULLABLE"},
{"name": "td_3156_820","type": "NUMERIC","mode": "NULLABLE"},
{"name": "td_3507_t","type": "NUMERIC","mode": "NULLABLE"},
{"name": "td_3507_1","type": "NUMERIC","mode": "NULLABLE"},
{"name": "td_3507_4","type": "NUMERIC","mode": "NULLABLE"},
{"name": "td_6385_t","type": "NUMERIC","mode": "NULLABLE"},
{"name": "td_6385_1","type": "NUMERIC","mode": "NULLABLE"},
{"name": "td_6385_4","type": "NUMERIC","mode": "NULLABLE"},
{"name": "td_tot1","type": "NUMERIC","mode": "NULLABLE"},
{"name": "td_3490_t","type": "NUMERIC","mode": "NULLABLE"},
{"name": "td_3490_1","type": "NUMERIC","mode": "NULLABLE"},
{"name": "td_3490_4","type": "NUMERIC","mode": "NULLABLE"},
{"name": "td_6370_t","type": "NUMERIC","mode": "NULLABLE"},
{"name": "td_6370_1","type": "NUMERIC","mode": "NULLABLE"},
{"name": "td_6370_4","type": "NUMERIC","mode": "NULLABLE"},
{"name": "td_tot2","type": "NUMERIC","mode": "NULLABLE"}

]