[
{"name": "fchinf","type": "DATE","mode": "NULLABLE"},
{"name": "version","type": "INTEGER","mode": "NULLABLE"},
{"name": "moneda","type": "INTEGER","mode": "NULLABLE"},
{"name": "cod_moneda","type": "STRING","mode": "NULLABLE"},
{"name": "producto","type": "STRING","mode": "NULLABLE"},
{"name": "descripcion","type": "STRING","mode": "NULLABLE"},
{"name": "intercompany_recibir","type": "NUMERIC","mode": "NULLABLE"},
{"name": "thirdparty_recibir","type": "NUMERIC","mode": "NULLABLE"},
{"name": "total_prod_recibir","type": "NUMERIC","mode": "NULLABLE"},
{"name": "intercompany_entregar","type": "NUMERIC","mode": "NULLABLE"},
{"name": "thirdparty_entregar","type": "NUMERIC","mode": "NULLABLE"},
{"name": "total_prod_entregar","type": "NUMERIC","mode": "NULLABLE"},
{"name": "orden","type": "INTEGER","mode": "NULLABLE"},
{"name": "origen","type": "STRING","mode": "NULLABLE"},
{"name": "fchreg","type": "DATE","mode": "NULLABLE"},
{"name": "horreg","type": "STRING","mode": "NULLABLE"},
{"name": "usureg","type": "STRING","mode": "NULLABLE"}

]